[
    /* --- FİLMLER (20 Adet) --- */
    {
        "id": 1,
        "type": "Film",
        "title": "Avengers: Endgame",
        "year": 2019,
        "category": "Süper Kahraman/Aksiyon",
        "rating": 8.4,
        "summary": "Avengers ekibinin, Thanos'u yenmek için son bir çabası.",
        "cast": ["Robert Downey Jr.", "Chris Evans"],
        "duration": "181 dk"
    },
    {
        "id": 2,
        "type": "Film",
        "title": "Frankenstein",
        "year": 1931,
        "category": "Gotik/Korku",
        "rating": 7.8,
        "summary": "Bir bilim adamının canlandırdığı yaratığın trajik hikayesi.",
        "cast": ["Boris Karloff", "Colin Clive"],
        "duration": "70 dk"
    },
    {
        "id": 3,
        "type": "Film",
        "title": "Upgrade",
        "year": 2018,
        "category": "Aksiyon/Bilim Kurgu",
        "rating": 7.5,
        "summary": "Yapay zeka çipi sayesinde süper insan yetenekleri kazanan bir adamın intikamı.",
        "cast": ["Logan Marshall-Green", "Betty Gabriel"],
        "duration": "100 dk"
    },
    {
        "id": 4,
        "type": "Film",
        "title": "Oksijen",
        "year": 2021,
        "category": "Bilim Kurgu/Gerilim",
        "rating": 6.5,
        "summary": "Kapalı bir kriyojenik ünitede uyanan ve kim olduğunu hatırlamayan bir kadın.",
        "cast": ["Mélanie Laurent", "Mathieu Amalric"],
        "duration": "101 dk"
    },
    {
        "id": 5,
        "type": "Film",
        "title": "Yıldızlararası",
        "year": 2014,
        "category": "Bilim Kurgu",
        "rating": 8.6,
        "summary": "İnsanlığın hayatta kalması için solucan deliğinden geçen bir grup kaşif...",
        "cast": ["Matthew McConaughey", "Anne Hathaway"],
        "duration": "169 dk"
    },
    {
        "id": 6,
        "type": "Film",
        "title": "Gladyatör",
        "year": 2000,
        "category": "Tarihi/Aksiyon",
        "rating": 8.5,
        "summary": "General Maximus'un intikam hikayesi.",
        "cast": ["Russell Crowe", "Joaquin Phoenix"],
        "duration": "155 dk"
    },
    {
        "id": 7,
        "type": "Film",
        "title": "Yeşil Yol",
        "year": 1999,
        "category": "Dram",
        "rating": 8.6,
        "summary": "Bir hapishane gardiyanının mucizevi güçlere sahip bir mahkumla karşılaşması.",
        "cast": ["Tom Hanks", "Michael Clarke Duncan"],
        "duration": "189 dk"
    },
    {
        "id": 8,
        "type": "Film",
        "title": "Matrix",
        "year": 1999,
        "category": "Bilim Kurgu/Aksiyon",
        "rating": 8.7,
        "summary": "Bilgisayar programcısı Neo'nun gerçekliği sorgulamaya başlaması.",
        "cast": ["Keanu Reeves", "Laurence Fishburne"],
        "duration": "136 dk"
    },
    {
        "id": 9,
        "type": "Film",
        "title": "Geleceğe Dönüş",
        "year": 1985,
        "category": "Bilim Kurgu/Macera",
        "rating": 8.5,
        "summary": "Marty McFly'ın zaman yolculuğu macerası.",
        "cast": ["Michael J. Fox", "Christopher Lloyd"],
        "duration": "116 dk"
    },
    {
        "id": 10,
        "type": "Film",
        "title": "Başlangıç",
        "year": 2010,
        "category": "Aksiyon/Gizem",
        "rating": 8.8,
        "summary": "Rüyalar içinde rüyalar yaratarak fikir çalma sanatı.",
        "cast": ["Leonardo DiCaprio", "Joseph Gordon-Levitt"],
        "duration": "148 dk"
    },
    {
        "id": 11,
        "type": "Film",
        "title": "Yüzüklerin Efendisi: İki Kule",
        "year": 2002,
        "category": "Fantastik/Macera",
        "rating": 8.7,
        "summary": "Yüzük kardeşliğinin ayrılması ve Frodo'nun yolculuğuna devam etmesi.",
        "cast": ["Elijah Wood", "Ian McKellen"],
        "duration": "179 dk"
    },
    {
        "id": 12,
        "type": "Film",
        "title": "Dövüş Kulübü",
        "year": 1999,
        "category": "Dram/Gerilim",
        "rating": 8.8,
        "summary": "Uykusuzluk çeken bir adamın Tyler Durden ile tanışması.",
        "cast": ["Brad Pitt", "Edward Norton"],
        "duration": "139 dk"
    },
    {
        "id": 13,
        "type": "Film",
        "title": "Godfather",
        "year": 1972,
        "category": "Suç/Dram",
        "rating": 9.2,
        "summary": "Corleone ailesinin hikayesi ve baba Vito Corleone'nin değişimi.",
        "cast": ["Marlon Brando", "Al Pacino"],
        "duration": "175 dk"
    },
    {
        "id": 14,
        "type": "Film",
        "title": "Prestij",
        "year": 2006,
        "category": "Gizem/Gerilim",
        "rating": 8.5,
        "summary": "İki sihirbazın birbirini alt etme takıntısı.",
        "cast": ["Hugh Jackman", "Christian Bale"],
        "duration": "130 dk"
    },
    {
        "id": 15,
        "type": "Film",
        "title": "Forrest Gump",
        "year": 1994,
        "category": "Romantik/Dram",
        "rating": 8.8,
        "summary": "Düşük IQ'lu bir adamın Amerikan tarihine tanıklığı.",
        "cast": ["Tom Hanks", "Robin Wright"],
        "duration": "142 dk"
    },
    {
        "id": 16,
        "type": "Film",
        "title": "Terminatör 2",
        "year": 1991,
        "category": "Aksiyon/Bilim Kurgu",
        "rating": 8.6,
        "summary": "Gelecekten gelen robotların John Connor'ı koruma mücadelesi.",
        "cast": ["Arnold Schwarzenegger", "Linda Hamilton"],
        "duration": "137 dk"
    },
    {
        "id": 17,
        "type": "Film",
        "title": "Canım Kardeşim",
        "year": 1973,
        "category": "Dram/Yeşilçam",
        "rating": 9.0,
        "summary": "Fakir ve hayalperest ağabeyin, hasta kardeşinin son dileğini gerçekleştirme çabası.",
        "cast": ["Tarık Akan", "Halit Akçatepe"],
        "duration": "92 dk"
    },
    {
        "id": 18,
        "type": "Film",
        "title": "Hayat Güzeldir",
        "year": 1997,
        "category": "Savaş/Komedi-Dram",
        "rating": 8.6,
        "summary": "Holokost sırasında oğluna savaşın bir oyun olduğunu göstermeye çalışan baba.",
        "cast": ["Roberto Benigni", "Nicoletta Braschi"],
        "duration": "116 dk"
    },
    {
        "id": 19,
        "type": "Film",
        "title": "Joker",
        "year": 2019,
        "category": "Suç/Gerilim",
        "rating": 8.4,
        "summary": "Başarısız bir komedyenin Gotham'da nasıl kaosa dönüştüğünün hikayesi.",
        "cast": ["Joaquin Phoenix", "Robert De Niro"],
        "duration": "122 dk"
    },
    {
        "id": 20,
        "type": "Film",
        "title": "Parazit",
        "year": 2019,
        "category": "Komedi/Gerilim",
        "rating": 8.5,
        "summary": "İki ailenin yaşamının iç içe geçmesi.",
        "cast": ["Song Kang-ho", "Choi Woo-shik"],
        "duration": "132 dk"
    },
    
    /* --- DİZİLER (15 Adet) --- */
    {
        "id": 21,
        "type": "Dizi",
        "title": "3 Cisim Problemi",
        "year": 2024,
        "category": "Bilim Kurgu",
        "rating": 7.5,
        "summary": "Farklı zaman dilimlerinde geçen, insanlığın uzaylı istilasına karşı mücadelesi.",
        "cast": ["Jess Hong", "Eiza González"],
        "seasons": 1,
        "status": "Devam Ediyor"
    },
    {
        "id": 22,
        "type": "Dizi",
        "title": "Stranger Things",
        "year": 2016,
        "category": "Fantastik/Gerilim",
        "rating": 8.7,
        "summary": "Küçük bir kasabada kaybolan bir çocuk ve doğaüstü olaylar.",
        "cast": ["Millie Bobby Brown", "David Harbour"],
        "seasons": 4,
        "status": "Devam Ediyor"
    },
    {
        "id": 23,
        "type": "Dizi",
        "title": "Anne with an E",
        "year": 2017,
        "category": "Dram",
        "rating": 8.7,
        "summary": "19. yüzyılda yetim kalan Anne Shirley'nin maceraları.",
        "cast": ["Amybeth McNulty", "Geraldine James"],
        "seasons": 3,
        "status": "Bitti"
    },
    {
        "id": 24,
        "type": "Dizi",
        "title": "Sherlock",
        "year": 2010,
        "category": "Polisiye/Gizem",
        "rating": 9.1,
        "summary": "Modern Londra'da yaşayan dahi dedektif Sherlock Holmes.",
        "cast": ["Benedict Cumberbatch", "Martin Freeman"],
        "seasons": 4,
        "status": "Bitti"
    },
    {
        "id": 25,
        "type": "Dizi",
        "title": "Arcane",
        "year": 2021,
        "category": "Animasyon/Fantastik",
        "rating": 9.0,
        "summary": "Piltover ve Zaun şehirleri arasındaki çatışmanın kökenleri.",
        "cast": ["Ella Purnell", "Hailee Steinfeld"],
        "seasons": 1,
        "status": "Devam Ediyor"
    },
    {
        "id": 26,
        "type": "Dizi",
        "title": "The Queen's Gambit",
        "year": 2020,
        "category": "Dram",
        "rating": 8.6,
        "summary": "Yetimhanede büyüyen bir satranç dehasının yükselişi.",
        "cast": ["Anya Taylor-Joy", "Thomas Brodie-Sangster"],
        "seasons": 1,
        "status": "Bitti"
    },
    {
        "id": 27,
        "type": "Dizi",
        "title": "The Last of Us",
        "year": 2023,
        "category": "Post-apokaliptik",
        "rating": 9.2,
        "summary": "Küresel bir pandeminin ardından hayatta kalanlar.",
        "cast": ["Pedro Pascal", "Bella Ramsey"],
        "seasons": 1,
        "status": "Devam Ediyor"
    },
    {
        "id": 28,
        "type": "Dizi",
        "title": "Breaking Bad",
        "year": 2008,
        "category": "Suç/Dram",
        "rating": 9.5,
        "summary": "Kimya öğretmeninin uyuşturucu üreticisine dönüşmesi.",
        "cast": ["Bryan Cranston", "Aaron Paul"],
        "seasons": 5,
        "status": "Bitti"
    },
    {
        "id": 29,
        "type": "Dizi",
        "title": "Black Mirror",
        "year": 2011,
        "category": "Antoloji/Distopya",
        "rating": 8.8,
        "summary": "Modern toplumun teknolojiyle olan ilişkisini inceleyen karanlık hikayeler.",
        "cast": ["Çeşitli Oyuncular"],
        "seasons": 6,
        "status": "Devam Ediyor"
    },
    {
        "id": 30,
        "type": "Dizi",
        "title": "Mindhunter",
        "year": 2017,
        "category": "Gerilim/Polisiye",
        "rating": 8.6,
        "summary": "FBI ajanlarının seri katillerin psikolojisini incelemesi.",
        "cast": ["Jonathan Groff", "Holt McCallany"],
        "seasons": 2,
        "status": "Bitti"
    },
    {
        "id": 31,
        "type": "Dizi",
        "title": "Friends",
        "year": 1994,
        "category": "Komedi/Sitcom",
        "rating": 8.9,
        "summary": "New York'ta yaşayan bir grup arkadaşın hayatı.",
        "cast": ["Jennifer Aniston", "Matt LeBlanc"],
        "seasons": 10,
        "status": "Bitti"
    },
    {
        "id": 32,
        "type": "Dizi",
        "title": "Chernobyl",
        "year": 2019,
        "category": "Tarih/Dram",
        "rating": 9.4,
        "summary": "1986'daki nükleer felaketin dramatik hikayesi.",
        "cast": ["Jared Harris", "Stellan Skarsgård"],
        "seasons": 1,
        "status": "Bitti"
    },
    {
        "id": 33,
        "type": "Dizi",
        "title": "Game of Thrones",
        "year": 2011,
        "category": "Fantastik/Macera",
        "rating": 9.2,
        "summary": "Yedi krallığın taht mücadelesi.",
        "cast": ["Emilia Clarke", "Kit Harington"],
        "seasons": 8,
        "status": "Bitti"
    },
    {
        "id": 34,
        "type": "Dizi",
        "title": "Dexter",
        "year": 2006,
        "category": "Suç/Gerilim",
        "rating": 8.7,
        "summary": "Gündüz adli tıpçı, gece seri katil olan Dexter'ın hikayesi.",
        "cast": ["Michael C. Hall", "Jennifer Carpenter"],
        "seasons": 8,
        "status": "Bitti"
    },
    {
        "id": 35,
        "type": "Dizi",
        "title": "Peaky Blinders",
        "year": 2013,
        "category": "Tarihi/Suç",
        "rating": 8.8,
        "summary": "Birmingham'daki ünlü Peaky Blinders çetesinin yükselişi.",
        "cast": ["Cillian Murphy", "Sam Neill"],
        "seasons": 6,
        "status": "Bitti"
    },

    /* --- KİTAPLAR (15 Adet) --- */
    {
        "id": 36,
        "type": "Kitap",
        "title": "İnce Memed (1. Cilt)",
        "year": 1955,
        "category": "Türk Klasiği/Roman",
        "rating": 9.2,
        "summary": "Çukurova'daki eşitsizlik ve ağalık sistemine karşı çıkan bir kahramanın hikayesi.",
        "author": "Yaşar Kemal",
        "page_count": 395,
        "publisher": "Toros Yayınları"
    },
    {
        "id": 37,
        "type": "Kitap",
        "title": "Tutunamayanlar",
        "year": 1971,
        "category": "Türk Klasiği/Modern",
        "rating": 9.5,
        "summary": "Turgut Özben'in intihar eden arkadaşı Selim Işık'ın izini sürerken kendi varoluşunu sorgulaması.",
        "author": "Oğuz Atay",
        "page_count": 724,
        "publisher": "Sinan Yayınları"
    },
    {
        "id": 38,
        "type": "Kitap",
        "title": "Yeraltından Notlar",
        "year": 1864,
        "category": "Dünya Klasiği/Felsefi",
        "rating": 9.0,
        "summary": "Toplumdan soyutlanmış, bilinçli ve yoksul bir adamın monologları.",
        "author": "Fyodor Dostoyevski",
        "page_count": 176,
        "publisher": "Epoch"
    },
    {
        "id": 39,
        "type": "Kitap",
        "title": "Gurur ve Önyargı",
        "year": 1813,
        "category": "Dünya Klasiği/Romantik",
        "rating": 9.1,
        "summary": "Elizabeth Bennet ve Bay Darcy'nin yanlış anlamalarla dolu aşk hikayesi.",
        "author": "Jane Austen",
        "page_count": 400,
        "publisher": "T. Egerton"
    },
    {
        "id": 40,
        "type": "Kitap",
        "title": "Sefiller",
        "year": 1862,
        "category": "Tarihi Roman",
        "rating": 9.4,
        "summary": "Fransız ihtilali döneminde Jean Valjean'ın adalet arayışı.",
        "author": "Victor Hugo",
        "page_count": 1400,
        "publisher": "A. Lacroix"
    },
    {
        "id": 41,
        "type": "Kitap",
        "title": "1984",
        "year": 1949,
        "category": "Distopya/Roman",
        "rating": 9.2,
        "summary": "Totaliter bir rejim altında yaşayan Winston Smith'in hikayesi.",
        "author": "George Orwell",
        "page_count": 328,
        "publisher": "Secker & Warburg"
    },
    {
        "id": 42,
        "type": "Kitap",
        "title": "Kürk Mantolu Madonna",
        "year": 1943,
        "category": "Türk Klasiği/Roman",
        "rating": 9.1,
        "summary": "Raif Efendi'nin gizemli kadının tablosuyla karşılaşması.",
        "author": "Sabahattin Ali",
        "page_count": 177,
        "publisher": "Remzi Kitabevi"
    },
    {
        "id": 43,
        "type": "Kitap",
        "title": "Simyacı",
        "year": 1988,
        "category": "Felsefe/Roman",
        "rating": 8.2,
        "summary": "Endülüslü çoban Santiago'nun kendini keşfi.",
        "author": "Paulo Coelho",
        "page_count": 197,
        "publisher": "HarperOne"
    },
    {
        "id": 44,
        "type": "Kitap",
        "title": "Uçurtma Avcısı",
        "year": 2003,
        "category": "Dram",
        "rating": 8.9,
        "summary": "Afganistan'da geçen, iki çocuğun karmaşık dostluk ve ihanet hikayesi.",
        "author": "Khaled Hosseini",
        "page_count": 416,
        "publisher": "Riverhead Books"
    },
    {
        "id": 45,
        "type": "Kitap",
        "title": "Dune",
        "year": 1965,
        "category": "Bilim Kurgu/Roman",
        "rating": 9.0,
        "summary": "Çöl gezegeni Arrakis'te geçen politik ve ekolojik macera.",
        "author": "Frank Herbert",
        "page_count": 412,
        "publisher": "Chilton Books"
    },
    {
        "id": 46,
        "type": "Kitap",
        "title": "Küçük Prens",
        "year": 1943,
        "category": "Çocuk/Felsefe",
        "rating": 9.3,
        "summary": "Bir pilotun çölde Küçük Prens ile karşılaşması.",
        "author": "Antoine de Saint-Exupéry",
        "page_count": 96,
        "publisher": "Reynal & Hitchcock"
    },
    {
        "id": 47,
        "type": "Kitap",
        "title": "Yabancı",
        "year": 1942,
        "category": "Felsefi Roman",
        "rating": 8.8,
        "summary": "Albert Camus'nün absürdizmi anlatan eseri.",
        "author": "Albert Camus",
        "page_count": 123,
        "publisher": "Gallimard"
    },
    {
        "id": 48,
        "type": "Kitap",
        "title": "Suç ve Ceza",
        "year": 1866,
        "category": "Dünya Klasiği/Gerilim",
        "rating": 9.5,
        "summary": "Fakir bir öğrencinin işlediği cinayet ve vicdan azabı.",
        "author": "Fyodor Dostoyevski",
        "page_count": 671,
        "publisher": "The Russian Messenger"
    },
    {
        "id": 49,
        "type": "Kitap",
        "title": "Anna Karenina",
        "year": 1877,
        "category": "Romantik/Klasik",
        "rating": 9.1,
        "summary": "Rusya'da evli bir kadının Kont Vronski ile yaşadığı aşk hikayesi.",
        "author": "Leo Tolstoy",
        "page_count": 864,
        "publisher": "The Russian Messenger"
    },
    {
        "id": 50,
        "type": "Kitap",
        "title": "Fahrenheit 451",
        "year": 1953,
        "category": "Distopya/Bilim Kurgu",
        "rating": 8.7,
        "summary": "Kitapların yasaklandığı ve yakıldığı bir gelecekteki itfaiyeci.",
        "author": "Ray Bradbury",
        "page_count": 256,
        "publisher": "Ballantine Books"
    }
]